django_route/__init__.py
django_route/admin.py
django_route/apps.py
django_route/cache.py
django_route/conf/__init__.py
django_route/conf/global_settings.py
django_route/decorators.py
django_route/middlewares.py
django_route/migrations/0001_initial.py
django_route/migrations/0002_router_description.py
django_route/migrations/__init__.py
django_route/models.py
django_route/signals/__init__.py
django_route/signals/handlers.py
django_route/utils.py
django_route/validators.py
django_route-0.3.0.dist-info/LICENSE
django_route-0.3.0.dist-info/WHEEL
django_route-0.3.0.dist-info/METADATA
django_route-0.3.0.dist-info/RECORD
