Metadata-Version: 2.1
Name: django-route
Version: 0.3.0
Summary: Conditional url routing for django
Home-page: https://github.com/vinayinvicible/django-route
License: MIT
Author: Vinay Karanam
Author-email: vinayinvicible@gmail.com
Requires-Python: >=3.6,<4.0
Classifier: License :: OSI Approved :: MIT License
Classifier: Programming Language :: Python :: 3
Classifier: Programming Language :: Python :: 3.10
Classifier: Programming Language :: Python :: 3.6
Classifier: Programming Language :: Python :: 3.7
Classifier: Programming Language :: Python :: 3.8
Classifier: Programming Language :: Python :: 3.9
Requires-Dist: Django
Project-URL: Documentation, https://django-route.readthedocs.io/
Project-URL: Repository, https://github.com/vinayinvicible/django-route
